LICENSE
cpdd_dataset/__init__.py
cpdd_dataset/config/__init__.py
cpdd_dataset/config/_config.py
cpdd_dataset/config/_loader.py
cpdd_dataset/data/__init__.py
cpdd_dataset/data/_crop.py
cpdd_dataset/data/_location.py
cpdd_dataset/data/_run_data.py
cpdd_dataset/data/_side.py
cpdd_dataset/intrinsics/__init__.py
cpdd_dataset/intrinsics/_intrinsics.py
cpdd_dataset-0.1.3.dist-info/LICENSE
cpdd_dataset-0.1.3.dist-info/WHEEL
cpdd_dataset-0.1.3.dist-info/METADATA
cpdd_dataset-0.1.3.dist-info/RECORD
