Metadata-Version: 2.1
Name: cpdd-dataset
Version: 0.1.3
Summary: Accessors for CARLA Panoramic Depth Detection Dataset, the dataset created as part of my thesis
Home-page: https://github.com/rnett/cpdd-dataset
License: MIT
Author: Ryan Nett
Author-email: rnett@calpoly.edu
Requires-Python: >=3.7,<4.0
Classifier: License :: OSI Approved :: MIT License
Classifier: Programming Language :: Python :: 3
Classifier: Programming Language :: Python :: 3.7
Classifier: Programming Language :: Python :: 3.8
Classifier: Programming Language :: Python :: 3.9
Requires-Dist: h5py (>=2.10.0,<3.0.0)
Requires-Dist: numpy (>=1.18.1,<2.0.0)
Requires-Dist: pandas (>=1.0.0,<2.0.0)
Requires-Dist: s3fs (>=0.4.0,<0.5.0)
Project-URL: Repository, https://github.com/rnett/cpdd-dataset
